dar_backup/.darrc
dar_backup/Changelog.md
dar_backup/README.md
dar_backup/__about__.py
dar_backup/__init__.py
dar_backup/clean_log.py
dar_backup/cleanup.py
dar_backup/command_runner.py
dar_backup/config_settings.py
dar_backup/dar-backup.conf
dar_backup/dar-backup.conf.j2
dar_backup/dar_backup.py
dar_backup/dar_backup_systemd.py
dar_backup/demo.py
dar_backup/demo_backup_def.j2
dar_backup/exceptions.py
dar_backup/installer.py
dar_backup/manager.py
dar_backup/rich_progress.py
dar_backup/util.py
dar_backup-1.0.2.dist-info/METADATA
dar_backup-1.0.2.dist-info/WHEEL
dar_backup-1.0.2.dist-info/entry_points.txt
dar_backup-1.0.2.dist-info/licenses/LICENSE
dar_backup-1.0.2.dist-info/RECORD
