Metadata-Version: 2.4
Name: dar-backup
Version: 1.0.2
Summary: A script to do full, differential and incremental backups using dar.     Some files are restored from the backups during verification, after which par2 redundancy files are created.     The script also has a cleanup feature to remove old backups and par2 files.
Project-URL: GPG Public Key, https://keys.openpgp.org/search?q=dar-backup@pm.me
Project-URL: Homepage, https://github.com/per2jensen/dar-backup/tree/main/v2
Project-URL: Changelog, https://github.com/per2jensen/dar-backup/blob/main/v2/Changelog.md
Project-URL: Issues, https://github.com/per2jensen
Author-email: dar-backup <dar-backup@pm.me>
License:                     GNU GENERAL PUBLIC LICENSE
License-File: LICENSE
Classifier: Development Status :: 5 - Production/Stable
Classifier: Intended Audience :: End Users/Desktop
Classifier: License :: OSI Approved :: GNU General Public License v3 or later (GPLv3+)
Classifier: Operating System :: POSIX :: Linux
Classifier: Programming Language :: Python :: 3.11
Classifier: Topic :: System :: Archiving :: Backup
Requires-Python: >=3.11
Requires-Dist: argcomplete>=3.6.2
Requires-Dist: inputimeout>=1.0.4
Requires-Dist: jinja2>=3.1.6
Requires-Dist: rich>=13.0.0
Provides-Extra: dev
Requires-Dist: anyio>=4.4.0; extra == 'dev'
Requires-Dist: black>=25.1.0; extra == 'dev'
Requires-Dist: coverage>=7.8.2; extra == 'dev'
Requires-Dist: h11>=0.16.0; extra == 'dev'
Requires-Dist: httpcore>=0.17.3; extra == 'dev'
Requires-Dist: matplotlib>=3.10.3; extra == 'dev'
Requires-Dist: pandas>=2.3.0; extra == 'dev'
Requires-Dist: psutil>=7.0.0; extra == 'dev'
Requires-Dist: pytest; extra == 'dev'
Requires-Dist: pytest-cov>=6.1.1; extra == 'dev'
Requires-Dist: pytest-timeout>=2.4.0; extra == 'dev'
Requires-Dist: pytest>=8.4.0; extra == 'dev'
Requires-Dist: requests>=2.32.2; extra == 'dev'
Requires-Dist: wheel>=0.45.1; extra == 'dev'
Requires-Dist: zipp>=3.19.1; extra == 'dev'
Provides-Extra: packaging
Requires-Dist: build>=1.2.2; extra == 'packaging'
Requires-Dist: hatch>=1.14.1; extra == 'packaging'
Requires-Dist: hatchling>=1.27.0; extra == 'packaging'
Requires-Dist: twine>=6.1.0; extra == 'packaging'
